packagesource/__init__.py
packagesourceeeee-0.0.1.dist-info/METADATA
packagesourceeeee-0.0.1.dist-info/WHEEL
packagesourceeeee-0.0.1.dist-info/top_level.txt
packagesourceeeee-0.0.1.dist-info/RECORD
